{
"first":[{"code": "00","name": "一般职业"},
{"code": "01","name": "农牧业"},
{"code": "02","name": "渔业"},
{"code": "05","name": "交通运输业"},
{"code": "06","name": "餐饮旅游业"},
{"code": "07","name": "建筑工程"},
{"code": "08","name": "制造加工维修业"},
{"code": "09","name": "出版广告业"},
{"code": "10","name": "医药卫生保健"},
{"code": "11","name": "娱乐业"},
{"code": "12","name": "文教机构"},
{"code": "13","name": "宗教机构"},
{"code": "14","name": "公共事业"},
{"code": "15","name": "一般买卖（零售批发业）"},
{"code": "16","name": "服务业"},
{"code": "17","name": "家庭管理"},
{"code": "18","name": "公检法等执法检查机关"},
{"code": "19","name": "军人"},
{"code": "20","name": "IT业（软、硬件开发制作）"},
{"code": "21","name": "职业运动"},
{"code": "22","name": "其他"
}],
"second":[{"code": "0001","name": "机关团体公司"},
{"code": "0002","name": "工厂"},
{"code": "0101","name": "农业"},
{"code": "0102","name": "牧业"},
{"code": "0201","name": "内陆渔业"},
{"code": "0302","name": "木材加工业"},
{"code": "0303","name": "造林业"},
{"code": "0304","name": "农林牧渔服务业"},
{"code": "0402","name": "坑道外作业"},
{"code": "0405","name": "陆上油矿开采业"},
{"code": "0501","name": "陆运"},
{"code": "0502","name": "铁路"},
{"code": "0601","name": "旅游业"},
{"code": "0602","name": "旅馆业"},
{"code": "0603","name": "餐饮业"},
{"code": "0701","name": "建筑公司"},
{"code": "0702","name": "铁路公路铺设"},
{"code": "0703","name": "造修船业"},
{"code": "0705","name": "装璜业"},
{"code": "0707","name": "测绘工程"},
{"code": "0801","name": "冶金业"},
{"code": "0802","name": "机械制造维修业"},
{"code": "0803","name": "电子器械产品业"},
{"code": "0804","name": "电机业"},
{"code": "0806","name": "水泥业(包括水泥、石膏、石灰、陶器)"},
{"code": "0807","name": "化工业"},
{"code": "0809","name": "机动车、自行车制造业与修理业"},
{"code": "0810","name": "纺织印染及成衣业"},
{"code": "0811","name": "造纸工业"},
{"code": "0812","name": "家具制造业"},
{"code": "0813","name": "工艺品生产加工业"},
{"code": "0814","name": "电线电缆光缆制造业"},
{"code": "0815","name": "食品饮料烟草加工业"},
{"code": "0816","name": "家电制造维修业"},
{"code": "0818","name": "玻璃制造业"},
{"code": "0901","name": "出版印刷业"},
{"code": "0902","name": "广告业"},
{"code": "1001","name": "医疗卫生"},
{"code": "1002","name": "制药制剂业"},
{"code": "1101","name": "广播电影电视业"},
{"code": "1102","name": "高尔夫球馆"},
{"code": "1103","name": "保龄球馆"},
{"code": "1104","name": "撞球馆"},
{"code": "1105","name": "游泳池"},
{"code": "1106","name": "海水浴场"},
{"code": "1107","name": "其他游乐园"},
{"code": "1108","name": "艺术及演艺人员"},
{"code": "1109","name": "特种营业"},
{"code": "1201","name": "教育机构"},
{"code": "1202","name": "考古、文物保护及其他"},
{"code": "1300","name": "宗教人士"},
{"code": "1401","name": "邮政与通信"},
{"code": "1402","name": "电力"},
{"code": "1403","name": "自来水(水利)"},
{"code": "1404","name": "燃气"},
{"code": "1501","name": "买卖"},
{"code": "1601","name": "金融、保险、证券业"},
{"code": "1602","name": "自由业"},
{"code": "1603","name": "其他"},
{"code": "1701","name": "家政管理"},
{"code": "1801","name": "法院、检察院工作人员"},
{"code": "1802","name": "公安警务工作人员"},
{"code": "1901","name": "现役军人"},
{"code": "2001","name": "IT业（软、硬件开发制作）"},
{"code": "2101","name": "高尔夫球"},
{"code": "2102","name": "保龄球"},
{"code": "2103","name": "桌球"},
{"code": "2104","name": "乒乓球、羽毛球"},
{"code": "2105","name": "游泳"},
{"code": "2106","name": "射箭"},
{"code": "2107","name": "网球"},
{"code": "2108","name": "垒球"},
{"code": "2109","name": "溜冰"},
{"code": "2110","name": "射击"},
{"code": "2111","name": "民族体育活动(不含竞技性)"},
{"code": "2112","name": "举重"},
{"code": "2113","name": "篮球"},
{"code": "2114","name": "排球"},
{"code": "2115","name": "棒球"},
{"code": "2116","name": "田径"},
{"code": "2117","name": "体操"},
{"code": "2118","name": "滑雪"},
{"code": "2119","name": "帆船"},
{"code": "2120","name": "划船"},
{"code": "2121","name": "泛舟"},
{"code": "2122","name": "巧固球"},
{"code": "2123","name": "手球"},
{"code": "2124","name": "风浪板"},
{"code": "2125","name": "水上摩托车"},
{"code": "2126","name": "足球"},
{"code": "2127","name": "曲棍球"},
{"code": "2128","name": "冰上曲棍球"},
{"code": "2129","name": "橄榄球"},
{"code": "2130","name": "摔跤"},
{"code": "2131","name": "击剑"},
{"code": "2132","name": "拳击"},
{"code": "2133","name": "无业人员"
}]
}
